examples/adoptation/mnist_simple/cli/original.py
examples/adoptation/mnist_simple/cli/tractorun.py
examples/adoptation/mnist_simple/sdk/original.py
examples/adoptation/mnist_simple/sdk/tractorun.py
examples/jax/jax_simple/jax_simple.py
examples/jax/jax_simple_distributed/jax_simple_distributed.py
examples/pytorch/lightning_mnist/lightning_mnist.py
examples/pytorch/lightning_mnist_ddp/lightning_mnist_ddp.py
examples/pytorch/lightning_mnist_ddp_script/lightning_mnist_ddp_script.py
examples/pytorch/lightning_mnist_ddp_script_config/lightning_mnist_ddp_script_config.py
examples/pytorch/simple_distributed/simple_distributed.py
examples/pytorch/torch_mnist/torch_mnist.py
examples/pytorch/torch_mnist_checkpoints/torch_mnist_checkpoints.py
tests/__init__.py
tests/conftest.py
tests/utils.py
tests/yt_instances.py
tests/data/check_cypress_bind.py
tests/data/dummy_script.py
tests/data/env_script.py
tests/data/jax_run_script.py
tests/data/log_table_script.py
tests/data/restarting_sidecar_script.py
tests/data/sidecar_script.py
tests/data/stderr_script.py
tests/data/tensorproxy_script.py
tests/data/torch_run_script.py
tests/examples/__init__.py
tests/examples/test_examples.py
tests/generic/__init__.py
tests/generic/test_binds.py
tests/generic/test_cli.py
tests/generic/test_config.py
tests/generic/test_description.py
tests/generic/test_docker_auth.py
tests/generic/test_environment.py
tests/generic/test_mesh.py
tests/generic/test_operation_log.py
tests/generic/test_process_manager.py
tests/generic/test_project_structure.py
tests/generic/test_run.py
tests/generic/test_sidecars.py
tests/generic/test_stderr_reader.py
tests/generic/test_sync.py
tests/generic/test_title.py
tests/generic/test_yt_cluster.py
tests/tensorproxy/__init__.py
tests/tensorproxy/test_tensorproxy.py
tests/tractorax/__init__.py
tests/tractorax/test_project_structure.py
tests/tractorax/test_run.py
tests/tractorch/__init__.py
tests/tractorch/test_project_structure.py
tests/tractorch/test_run.py
tractorun/__init__.py
tractorun-0.62.0.dist-info/licenses/LICENSE
tractorun-0.62.0.dist-info/METADATA
tractorun-0.62.0.dist-info/WHEEL
tractorun-0.62.0.dist-info/entry_points.txt
tractorun-0.62.0.dist-info/top_level.txt
tractorun-0.62.0.dist-info/RECORD
